LICENSE
MANIFEST.in
README.md
setup.py
django_app_novadata/__init__.py
django_app_novadata/apps.py
django_app_novadata/tests.py
django_app_novadata/urls.py
django_app_novadata.egg-info/PKG-INFO
django_app_novadata.egg-info/SOURCES.txt
django_app_novadata.egg-info/dependency_links.txt
django_app_novadata.egg-info/top_level.txt
django_app_novadata/__pycache__/__init__.cpython-38.pyc
django_app_novadata/__pycache__/apps.cpython-38.pyc
django_app_novadata/__pycache__/urls.cpython-38.pyc
django_app_novadata/admin/__init__.py
django_app_novadata/admin/configuracao_autenticacao_admin.py
django_app_novadata/admin/conteudo_custom_admin.py
django_app_novadata/admin/__pycache__/__init__.cpython-38.pyc
django_app_novadata/admin/__pycache__/configuracao_autenticacao_admin.cpython-38.pyc
django_app_novadata/admin/__pycache__/conteudo_custom_admin.cpython-38.pyc
django_app_novadata/forms/__init__.py
django_app_novadata/managers/__init__.py
django_app_novadata/middlewares/__init__.py
django_app_novadata/migrations/0001_initial.py
django_app_novadata/migrations/0002_conteudocustom_logo.py
django_app_novadata/migrations/0003_alter_conteudocustom_local.py
django_app_novadata/migrations/0004_auto_20220719_1006.py
django_app_novadata/migrations/0005_remove_configuracaoautenticacao_extra_conteudo.py
django_app_novadata/migrations/0006_configuracaoautenticacao_extra_conteudo.py
django_app_novadata/migrations/0007_configuracaoautenticacao_local.py
django_app_novadata/migrations/0008_alter_configuracaoautenticacao_local.py
django_app_novadata/migrations/0009_alter_configuracaoautenticacao_local.py
django_app_novadata/migrations/0010_alter_configuracaoautenticacao_local.py
django_app_novadata/migrations/0011_auto_20220720_1328.py
django_app_novadata/migrations/0012_remove_configuracaoautenticacao_extra_conteudo.py
django_app_novadata/migrations/0013_configuracaoautenticacao_extra_style.py
django_app_novadata/migrations/__init__.py
django_app_novadata/migrations/__pycache__/0001_initial.cpython-38.pyc
django_app_novadata/migrations/__pycache__/0002_conteudocustom_logo.cpython-38.pyc
