Metadata-Version: 2.1
Name: django-app-novadata
Version: 0.1.1
Summary: Esta primeira versão traz um pacote que será utilizado para padronizar projetos distintos sem ser necessário modicação no código
Home-page: https://github.com/TimeNovaData/django_novadata.git
Author: Emanuel Morais
Author-email: emanuelbruno2018vasc@gmail.com
License: MIT License
Project-URL: Código fonte, https://github.com/TimeNovaData/django_novadata
Project-URL: Download, https://github.com/TimeNovaData/django_novadata.git
Keywords: Pacote
Platform: UNKNOWN
